Workbook

Sheet Dashboard
B2: Employee Attrition & Workforce Overview
B5: Total Employees | E5: Attrition Rate | H5: Avg Monthly Income | K5: Avg Tenure (yrs)
B6: =Summary!B2 -> 1478 | E6: =Summary!B4 -> 0.16170501 | H6: =Summary!B5 -> 49514.32 | K6: =Summary!B6 -> 7.0142084

Sheet HRData
A1: EmpID | B1: Age | C1: AgeGroup | D1: Attrition | E1: BusinessTravel | F1: DailyRate | G1: Department | H1: DistanceFromHome(KM) | I1: Education | J1: EducationField | K1: EmployeeNumber | L1: EnvironmentSatisfaction | M1: Gender | N1: JobInvolvement | O1: JobLevel | P1: JobRole | Q1: JobSatisfaction | R1: MaritalStatus | S1: MonthlyIncome | T1: SalarySlab | U1: HourlyRate | V1: NumCompaniesWorked | W1: OverTime | X1: SalaryHike % | Y1: PerformanceRating | Z1: RelationshipSatisfaction | AA1: StockOptionLevel | AB1: TotalExperience(Years) | AC1: TrainingsLastYear | AD1: WorkLifeBalance | AE1: YearsatCompany | AF1: YearsinCurrentRole | AG1: YearsSincePromotion | AH1: YearsWithCurrManager | AI1: AttritionFlag | AJ1: TenureBand | AK1: PromotionOverdue | AL1: FlightRiskScore | AM1: FlightRiskTier | AN1: IncomeVsRoleAvg | AO1: AnnualIncome
A2: VK2970 | B2: 19 | C2: 18-25 | D2: Yes | E2: Travel_Rarely | F2: 230 | G2: Administration | H2: 3 | I2: 3 | J2: Life Sciences | K2: 405 | L2: 3 | M2: Male | N2: 3 | O2: 1 | P2: Laboratory Technician | Q2: 3 | R2: Single | S2: 16795 | T2: 0-3 LPA | U2: 104.97 | V2: 1 | W2: No | X2: 13 | Y2: 3 | Z2: 3 | AA2: 0 | AB2: 0 | AC2: 2 | AD2: 3 | AE2: 0 | AF2: 0 | AG2: 0 | AH2: 0 | AI2: 1 | AJ2: 0-1 yr | AK2: Recent | AL2: 0 | AM2: Minimal Risk | AN2: -0.67527445 | AO2: 201540
A3: VK3020 | B3: 19 | C3: 18-25 | D3: No | E3: Travel_Rarely | F3: 812 | G3: Sales | H3: 10 | I3: 3 | J3: Medical | K3: 411 | L3: 4 | M3: Female | N3: 2 | O3: 1 | P3: Sales Representative | Q3: 3 | R3: Single | S3: 1860 | T3: 0-3 LPA | U3: 11.62 | V3: 1 | W3: No | X3: 12 | Y3: 3 | Z3: 1 | AA3: 0 | AB3: 0 | AC3: 2 | AD3: 3 | AE3: 0 | AF3: 0 | AG3: 0 | AH3: 0 | AI3: 0 | AJ3: 0-1 yr | AK3: Recent | AL3: 0 | AM3: Minimal Risk | AN3: -0.9622923 | AO3: 22320
A4: VK4580 | B4: 19 | C4: 18-25 | D4: Yes | E4: Travel_Frequently | F4: 1306 | G4: Sales | H4: 5 | I4: 3 | J4: Marketing | K4: 614 | L4: 2 | M4: Male | N4: 3 | O4: 1 | P4: Sales Representative | Q4: 2 | R4: Single | S4: 77820 | T4: 6-10 LPA | U4: 486.38 | V4: 1 | W4: Yes | X4: 14 | Y4: 3 | Z4: 4 | AA4: 0 | AB4: 0 | AC4: 3 | AD4: 3 | AE4: 0 | AF4: 0 | AG4: 0 | AH4: 0 | AI4: 1 | AJ4: 0-1 yr | AK4: Recent | AL4: 2 | AM4: Medium Risk | AN4: 0.57764144 | AO4: 933840
A5: VK7280 | B5: 19 | C5: 18-25 | D5: No | E5: Non_Travel | F5: 287 | G5: Administration | H5: 5 | I5: 2 | J5: Life Sciences | K5: 1012 | L5: 2 | M5: Male | N5: 3 | O5: 1 | P5: Research Scientist | Q5: 4 | R5: Single | S5: 55886 | T5: 6-10 LPA | U5: 349.29 | V5: 1 | W5: No | X5: 15 | Y5: 3 | Z5: 4 | AA5: 0 | AB5: 0 | AC5: 2 | AD5: 3 | AE5: 0 | AF5: 0 | AG5: 0 | AH5: 0 | AI5: 0 | AJ5: 0-1 yr | AK5: Recent | AL5: 0 | AM5: Minimal Risk | AN5: 0.12072124 | AO5: 670632
A6: VK8290 | B6: 19 | C6: 18-25 | D6: Yes | E6: Non_Travel | F6: 247 | G6: Administration | H6: 8 | I6: 1 | J6: Medical | K6: 1156 | L6: 3 | M6: Male | N6: 3 | O6: 1 | P6: Laboratory Technician | Q6: 3 | R6: Single | S6: 7265 | T6: 0-3 LPA | U6: 45.41 | V6: 1 | W6: No | X6: 12 | Y6: 3 | Z6: 4 | AA6: 0 | AB6: 0 | AC6: 0 | AD6: 3 | AE6: 0 | AF6: 0 | AG6: 0 | AH6: 0 | AI6: 1 | AJ6: 0-1 yr | AK6: Recent | AL6: 0 | AM6: Minimal Risk | AN6: -0.85953372 | AO6: 87180
A7: VK9730 | B7: 19 | C7: 18-25 | D7: No | E7: Non_Travel | F7: 1124 | G7: Administration | H7: 1 | I7: 3 | J7: Life Sciences | K7: 1368 | L7: 4 | M7: Female | N7: 3 | O7: 1 | P7: Laboratory Technician | Q7: 4 | R7: Single | S7: 83386 | T7: 10+ LPA | U7: 521.16 | V7: 1 | W7: No | X7: 15 | Y7: 3 | Z7: 3 | AA7: 0 | AB7: 0 | AC7: 5 | AD7: 4 | AE7: 0 | AF7: 0 | AG7: 0 | AH7: 0 | AI7: 0 | AJ7: 0-1 yr | AK7: Recent | AL7: 0 | AM7: Minimal Risk | AN7: 0.61223966 | AO7: 1000632
A8: VK11540 | B8: 19 | C8: 18-25 | D8: Yes | E8: Travel_Frequently | F8: 544 | G8: Sales | H8: 3 | I8: 2 | J8: Medical | K8: 1624 | L8: 2 | M8: Female | N8: 3 | O8: 1 | P8: Sales Representative | Q8: 4 | R8: Single | S8: 38194 | T8: 3-6 LPA | U8: 238.71 | V8: 1 | W8: Yes | X8: 12 | Y8: 3 | Z8: 3 | AA8: 0 | AB8: 0 | AC8: 2 | AD8: 4 | AE8: 0 | AF8: 0 | AG8: 0 | AH8: 0 | AI8: 1 | AJ8: 0-1 yr | AK8: Recent | AL8: 1 | AM8: Low Risk | AN8: -0.22569472 | AO8: 458328
A9: VK13120 | B9: 19 | C9: 18-25 | D9: No | E9: Non_Travel | F9: 1431 | G9: Administration | H9: 14 | I9: 3 | J9: Medical | K9: 1839 | L9: 2 | M9: Female | N9: 3 | O9: 1 | P9: Research Scientist | Q9: 3 | R9: Single | S9: 88498 | T9: 10+ LPA | U9: 553.11 | V9: 1 | W9: No | X9: 16 | Y9: 3 | Z9: 3 | AA9: 0 | AB9: 0 | AC9: 4 | AD9: 1 | AE9: 0 | AF9: 0 | AG9: 0 | AH9: 0 | AI9: 0 | AJ9: 0-1 yr | AK9: Recent | AL9: 1 | AM9: Low Risk | AN9: 0.7747126 | AO9: 1061976
A10: VK1280 | B10: 19 | C10: 18-25 | D10: Yes | E10: Travel_Rarely | F10: 528 | G10: Sales | H10: 22 | I10: 1 | J10: Marketing | K10: 167 | L10: 4 | M10: Male | N10: 3 | O10: 1 | P10: Sales Representative | Q10: 3 | R10: Single | S10: 45131 | T10: 3-6 LPA | U10: 282.07 | V10: 1 | W10: Yes | X10: 19 | Y10: 3 | Z10: 4 | AA10: 0 | AB10: 0 | AC10: 2 | AD10: 2 | AE10: 0 | AF10: 0 | AG10: 0 | AH10: 0 | AI10: 1 | AJ10: 0-1 yr | AK10: Recent | AL10: 2 | AM10: Medium Risk | AN10: -0.085061221 | AO10: 541572
A11: VK1500 | B11: 19 | C11: 18-25 | D11: No | E11: Travel_Rarely | F11: 1181 | G11: Administration | H11: 3 | I11: 1 | J11: Medical | K11: 201 | L11: 2 | M11: Female | N11: 3 | O11: 1 | P11: Laboratory Technician | Q11: 2 | R11: Single | S11: 61263 | T11: 6-10 LPA | U11: 382.89 | V11: 1 | W11: No | X11: 14 | Y11: 3 | Z11: 4 | AA11: 0 | AB11: 1 | AC11: 3 | AD11: 3 | AE11: 1 | AF11: 0 | AG11: 0 | AH11: 0 | AI11: 0 | AJ11: 0-1 yr | AK11: Recent | AL11: 1 | AM11: Low Risk | AN11: 0.18449906 | AO11: 735156
A12: VK1720 | B12: 19 | C12: 18-25 | D12: Yes | E12: Travel_Frequently | F12: 602 | G12: Sales | H12: 1 | I12: 1 | J12: Technical Degree | K12: 235 | L12: 3 | M12: Female | N12: 1 | O12: 1 | P12: Sales Representative | Q12: 1 | R12: Single | S12: 17023 | T12: 0-3 LPA | U12: 106.39 | V12: 0 | W12: No | X12: 21 | Y12: 4 | Z12: 1 | AA12: 0 | AB12: 1 | AC12: 5 | AD12: 4 | AE12: 0 | AF12: 0 | AG12: 0 | AH12: 0 | AI12: 1 | AJ12: 0-1 yr | AK12: Recent | AL12: 1 | AM12: Low Risk | AN12: -0.65489347 | AO12: 204276
A13: VK1780 | B13: 19 | C13: 18-25 | D13: Yes | E13: Travel_Rarely | F13: 303 | G13: Administration | H13: 2 | I13: 3 | J13: Life Sciences | K13: 243 | L13: 2 | M13: Male | N13: 2 | O13: 1 | P13: Laboratory Technician | Q13: 4 | R13: Single | S13: 42090 | T13: 3-6 LPA | U13: 263.06 | V13: 1 | W13: No | X13: 22 | Y13: 4 | Z13: 3 | AA13: 0 | AB13: 1 | AC13: 3 | AD13: 2 | AE13: 1 | AF13: 0 | AG13: 1 | AH13: 0 | AI13: 1 | AJ13: 0-1 yr | AK13: Recent | AL13: 1 | AM13: Low Risk | AN13: -0.18620431 | AO13: 505080
... A1479: VK12100 | B1479: 60 | C1479: 55+ | D1479: No | E1479: Travel_Rarely | F1479: 370 | G1479: Operations | H1479: 1 | I1479: 4 | J1479: Medical | K1479: 1697 | L1479: 3 | M1479: Male | N1479: 1 | O1479: 3 | P1479: Healthcare Representative | Q1479: 4 | R1479: Single | S1479: 87123 | T1479: 10+ LPA | U1479: 544.52 | V1479: 3 | W1479: No | X1479: 20 | Y1479: 4 | Z1479: 3 | AA1479: 1 | AB1479: 19 | AC1479: 2 | AD1479: 4 | AE1479: 1 | AF1479: 0 | AG1479: 0 | AH1479: 0 | AI1479: 0 | AJ1479: 0-1 yr | AK1479: Recent | AL1479: 0 | AM1479: Minimal Risk | AN1479: 0.80793836 | AO1479: 1045476

Sheet Data
A1: EmpID | B1: Age | C1: AgeGroup | D1: Attrition | E1: BusinessTravel | F1: DailyRate | G1: Department | H1: DistanceFromHome(KM) | I1: Education | J1: EducationField | K1: EmployeeNumber | L1: EnvironmentSatisfaction | M1: Gender | N1: JobInvolvement | O1: JobLevel | P1: JobRole | Q1: JobSatisfaction | R1: MaritalStatus | S1: MonthlyIncome | T1: SalarySlab | U1: HourlyRate | V1: NumCompaniesWorked | W1: OverTime | X1: SalaryHike % | Y1: PerformanceRating | Z1: RelationshipSatisfaction | AA1: StockOptionLevel | AB1: TotalExperience(Years) | AC1: TrainingsLastYear | AD1: WorkLifeBalance | AE1: YearsatCompany | AF1: YearsinCurrentRole | AG1: YearsSincePromotion | AH1: YearsWithCurrManager | AI1: AttritionFlag | AJ1: TenureBand | AK1: PromotionOverdue | AL1: FlightRiskScore | AM1: FlightRiskTier | AN1: IncomeVsRoleAvg | AO1: AnnualIncome
A2: VK2970 | B2: 19 | C2: 18-25 | D2: Yes | E2: Travel_Rarely | F2: 230 | G2: Administration | H2: 3 | I2: 3 | J2: Life Sciences | K2: 405 | L2: 3 | M2: Male | N2: 3 | O2: 1 | P2: Laboratory Technician | Q2: 3 | R2: Single | S2: 16795 | T2: 0-3 LPA | U2: 104.97 | V2: 1 | W2: No | X2: 13 | Y2: 3 | Z2: 3 | AA2: 0 | AB2: 0 | AC2: 2 | AD2: 3 | AE2: 0 | AF2: 0 | AG2: 0 | AH2: 0 | AI2: =IF(D2="Yes",1,0) -> 1 | AJ2: =IF(AE2<=1,"0-1 yr",IF(AE2<=3,"2-3 yrs",IF(AE2<=5,"4-5 yrs",IF(AE2<=10,"6-10 yrs","10+ yrs")))) -> 0-1 yr | AK2: =IF(AG2>=3,"Overdue","Recent") -> Recent | AL2: =IF(W2="Yes",1,0)+IF(AD2<=2,1,0)+IF(Q2<=2,1,0)+IF(AG2>=3,1,0) -> 0 | AM2: =IF(AL2>=3,"High Risk",IF(AL2=2,"Medium Risk",IF(AL2=1,"Low Risk","Minimal Risk"))) -> Minimal Risk | AN2: =IFERROR((S2-AVERAGEIF(P$2:P$1479,P2,S$2:S$1479))/AVERAGEIF(P$2:P$1479,P2,S$2:S$1479),0) -> -0.67527445 | AO2: =S2*12 -> 201540
A3: VK3020 | B3: 19 | C3: 18-25 | D3: No | E3: Travel_Rarely | F3: 812 | G3: Sales | H3: 10 | I3: 3 | J3: Medical | K3: 411 | L3: 4 | M3: Female | N3: 2 | O3: 1 | P3: Sales Representative | Q3: 3 | R3: Single | S3: 1860 | T3: 0-3 LPA | U3: 11.62 | V3: 1 | W3: No | X3: 12 | Y3: 3 | Z3: 1 | AA3: 0 | AB3: 0 | AC3: 2 | AD3: 3 | AE3: 0 | AF3: 0 | AG3: 0 | AH3: 0 | AI3: =IF(D3="Yes",1,0) -> 0 | AJ3: =IF(AE3<=1,"0-1 yr",IF(AE3<=3,"2-3 yrs",IF(AE3<=5,"4-5 yrs",IF(AE3<=10,"6-10 yrs","10+ yrs")))) -> 0-1 yr | AK3: =IF(AG3>=3,"Overdue","Recent") -> Recent | AL3: =IF(W3="Yes",1,0)+IF(AD3<=2,1,0)+IF(Q3<=2,1,0)+IF(AG3>=3,1,0) -> 0 | AM3: =IF(AL3>=3,"High Risk",IF(AL3=2,"Medium Risk",IF(AL3=1,"Low Risk","Minimal Risk"))) -> Minimal Risk | AN3: =IFERROR((S3-AVERAGEIF(P$2:P$1479,P3,S$2:S$1479))/AVERAGEIF(P$2:P$1479,P3,S$2:S$1479),0) -> -0.9622923 | AO3: =S3*12 -> 22320
A4: VK4580 | B4: 19 | C4: 18-25 | D4: Yes | E4: Travel_Frequently | F4: 1306 | G4: Sales | H4: 5 | I4: 3 | J4: Marketing | K4: 614 | L4: 2 | M4: Male | N4: 3 | O4: 1 | P4: Sales Representative | Q4: 2 | R4: Single | S4: 77820 | T4: 6-10 LPA | U4: 486.38 | V4: 1 | W4: Yes | X4: 14 | Y4: 3 | Z4: 4 | AA4: 0 | AB4: 0 | AC4: 3 | AD4: 3 | AE4: 0 | AF4: 0 | AG4: 0 | AH4: 0 | AI4: =IF(D4="Yes",1,0) -> 1 | AJ4: =IF(AE4<=1,"0-1 yr",IF(AE4<=3,"2-3 yrs",IF(AE4<=5,"4-5 yrs",IF(AE4<=10,"6-10 yrs","10+ yrs")))) -> 0-1 yr | AK4: =IF(AG4>=3,"Overdue","Recent") -> Recent | AL4: =IF(W4="Yes",1,0)+IF(AD4<=2,1,0)+IF(Q4<=2,1,0)+IF(AG4>=3,1,0) -> 2 | AM4: =IF(AL4>=3,"High Risk",IF(AL4=2,"Medium Risk",IF(AL4=1,"Low Risk","Minimal Risk"))) -> Medium Risk | AN4: =IFERROR((S4-AVERAGEIF(P$2:P$1479,P4,S$2:S$1479))/AVERAGEIF(P$2:P$1479,P4,S$2:S$1479),0) -> 0.57764144 | AO4: =S4*12 -> 933840
A5: VK7280 | B5: 19 | C5: 18-25 | D5: No | E5: Non_Travel | F5: 287 | G5: Administration | H5: 5 | I5: 2 | J5: Life Sciences | K5: 1012 | L5: 2 | M5: Male | N5: 3 | O5: 1 | P5: Research Scientist | Q5: 4 | R5: Single | S5: 55886 | T5: 6-10 LPA | U5: 349.29 | V5: 1 | W5: No | X5: 15 | Y5: 3 | Z5: 4 | AA5: 0 | AB5: 0 | AC5: 2 | AD5: 3 | AE5: 0 | AF5: 0 | AG5: 0 | AH5: 0 | AI5: =IF(D5="Yes",1,0) -> 0 | AJ5: =IF(AE5<=1,"0-1 yr",IF(AE5<=3,"2-3 yrs",IF(AE5<=5,"4-5 yrs",IF(AE5<=10,"6-10 yrs","10+ yrs")))) -> 0-1 yr | AK5: =IF(AG5>=3,"Overdue","Recent") -> Recent | AL5: =IF(W5="Yes",1,0)+IF(AD5<=2,1,0)+IF(Q5<=2,1,0)+IF(AG5>=3,1,0) -> 0 | AM5: =IF(AL5>=3,"High Risk",IF(AL5=2,"Medium Risk",IF(AL5=1,"Low Risk","Minimal Risk"))) -> Minimal Risk | AN5: =IFERROR((S5-AVERAGEIF(P$2:P$1479,P5,S$2:S$1479))/AVERAGEIF(P$2:P$1479,P5,S$2:S$1479),0) -> 0.12072124 | AO5: =S5*12 -> 670632
A6: VK8290 | B6: 19 | C6: 18-25 | D6: Yes | E6: Non_Travel | F6: 247 | G6: Administration | H6: 8 | I6: 1 | J6: Medical | K6: 1156 | L6: 3 | M6: Male | N6: 3 | O6: 1 | P6: Laboratory Technician | Q6: 3 | R6: Single | S6: 7265 | T6: 0-3 LPA | U6: 45.41 | V6: 1 | W6: No | X6: 12 | Y6: 3 | Z6: 4 | AA6: 0 | AB6: 0 | AC6: 0 | AD6: 3 | AE6: 0 | AF6: 0 | AG6: 0 | AH6: 0 | AI6: =IF(D6="Yes",1,0) -> 1 | AJ6: =IF(AE6<=1,"0-1 yr",IF(AE6<=3,"2-3 yrs",IF(AE6<=5,"4-5 yrs",IF(AE6<=10,"6-10 yrs","10+ yrs")))) -> 0-1 yr | AK6: =IF(AG6>=3,"Overdue","Recent") -> Recent | AL6: =IF(W6="Yes",1,0)+IF(AD6<=2,1,0)+IF(Q6<=2,1,0)+IF(AG6>=3,1,0) -> 0 | AM6: =IF(AL6>=3,"High Risk",IF(AL6=2,"Medium Risk",IF(AL6=1,"Low Risk","Minimal Risk"))) -> Minimal Risk | AN6: =IFERROR((S6-AVERAGEIF(P$2:P$1479,P6,S$2:S$1479))/AVERAGEIF(P$2:P$1479,P6,S$2:S$1479),0) -> -0.85953372 | AO6: =S6*12 -> 87180
A7: VK9730 | B7: 19 | C7: 18-25 | D7: No | E7: Non_Travel | F7: 1124 | G7: Administration | H7: 1 | I7: 3 | J7: Life Sciences | K7: 1368 | L7: 4 | M7: Female | N7: 3 | O7: 1 | P7: Laboratory Technician | Q7: 4 | R7: Single | S7: 83386 | T7: 10+ LPA | U7: 521.16 | V7: 1 | W7: No | X7: 15 | Y7: 3 | Z7: 3 | AA7: 0 | AB7: 0 | AC7: 5 | AD7: 4 | AE7: 0 | AF7: 0 | AG7: 0 | AH7: 0 | AI7: =IF(D7="Yes",1,0) -> 0 | AJ7: =IF(AE7<=1,"0-1 yr",IF(AE7<=3,"2-3 yrs",IF(AE7<=5,"4-5 yrs",IF(AE7<=10,"6-10 yrs","10+ yrs")))) -> 0-1 yr | AK7: =IF(AG7>=3,"Overdue","Recent") -> Recent | AL7: =IF(W7="Yes",1,0)+IF(AD7<=2,1,0)+IF(Q7<=2,1,0)+IF(AG7>=3,1,0) -> 0 | AM7: =IF(AL7>=3,"High Risk",IF(AL7=2,"Medium Risk",IF(AL7=1,"Low Risk","Minimal Risk"))) -> Minimal Risk | AN7: =IFERROR((S7-AVERAGEIF(P$2:P$1479,P7,S$2:S$1479))/AVERAGEIF(P$2:P$1479,P7,S$2:S$1479),0) -> 0.61223966 | AO7: =S7*12 -> 1000632
A8: VK11540 | B8: 19 | C8: 18-25 | D8: Yes | E8: Travel_Frequently | F8: 544 | G8: Sales | H8: 3 | I8: 2 | J8: Medical | K8: 1624 | L8: 2 | M8: Female | N8: 3 | O8: 1 | P8: Sales Representative | Q8: 4 | R8: Single | S8: 38194 | T8: 3-6 LPA | U8: 238.71 | V8: 1 | W8: Yes | X8: 12 | Y8: 3 | Z8: 3 | AA8: 0 | AB8: 0 | AC8: 2 | AD8: 4 | AE8: 0 | AF8: 0 | AG8: 0 | AH8: 0 | AI8: =IF(D8="Yes",1,0) -> 1 | AJ8: =IF(AE8<=1,"0-1 yr",IF(AE8<=3,"2-3 yrs",IF(AE8<=5,"4-5 yrs",IF(AE8<=10,"6-10 yrs","10+ yrs")))) -> 0-1 yr | AK8: =IF(AG8>=3,"Overdue","Recent") -> Recent | AL8: =IF(W8="Yes",1,0)+IF(AD8<=2,1,0)+IF(Q8<=2,1,0)+IF(AG8>=3,1,0) -> 1 | AM8: =IF(AL8>=3,"High Risk",IF(AL8=2,"Medium Risk",IF(AL8=1,"Low Risk","Minimal Risk"))) -> Low Risk | AN8: =IFERROR((S8-AVERAGEIF(P$2:P$1479,P8,S$2:S$1479))/AVERAGEIF(P$2:P$1479,P8,S$2:S$1479),0) -> -0.22569472 | AO8: =S8*12 -> 458328
A9: VK13120 | B9: 19 | C9: 18-25 | D9: No | E9: Non_Travel | F9: 1431 | G9: Administration | H9: 14 | I9: 3 | J9: Medical | K9: 1839 | L9: 2 | M9: Female | N9: 3 | O9: 1 | P9: Research Scientist | Q9: 3 | R9: Single | S9: 88498 | T9: 10+ LPA | U9: 553.11 | V9: 1 | W9: No | X9: 16 | Y9: 3 | Z9: 3 | AA9: 0 | AB9: 0 | AC9: 4 | AD9: 1 | AE9: 0 | AF9: 0 | AG9: 0 | AH9: 0 | AI9: =IF(D9="Yes",1,0) -> 0 | AJ9: =IF(AE9<=1,"0-1 yr",IF(AE9<=3,"2-3 yrs",IF(AE9<=5,"4-5 yrs",IF(AE9<=10,"6-10 yrs","10+ yrs")))) -> 0-1 yr | AK9: =IF(AG9>=3,"Overdue","Recent") -> Recent | AL9: =IF(W9="Yes",1,0)+IF(AD9<=2,1,0)+IF(Q9<=2,1,0)+IF(AG9>=3,1,0) -> 1 | AM9: =IF(AL9>=3,"High Risk",IF(AL9=2,"Medium Risk",IF(AL9=1,"Low Risk","Minimal Risk"))) -> Low Risk | AN9: =IFERROR((S9-AVERAGEIF(P$2:P$1479,P9,S$2:S$1479))/AVERAGEIF(P$2:P$1479,P9,S$2:S$1479),0) -> 0.7747126 | AO9: =S9*12 -> 1061976
A10: VK1280 | B10: 19 | C10: 18-25 | D10: Yes | E10: Travel_Rarely | F10: 528 | G10: Sales | H10: 22 | I10: 1 | J10: Marketing | K10: 167 | L10: 4 | M10: Male | N10: 3 | O10: 1 | P10: Sales Representative | Q10: 3 | R10: Single | S10: 45131 | T10: 3-6 LPA | U10: 282.07 | V10: 1 | W10: Yes | X10: 19 | Y10: 3 | Z10: 4 | AA10: 0 | AB10: 0 | AC10: 2 | AD10: 2 | AE10: 0 | AF10: 0 | AG10: 0 | AH10: 0 | AI10: =IF(D10="Yes",1,0) -> 1 | AJ10: =IF(AE10<=1,"0-1 yr",IF(AE10<=3,"2-3 yrs",IF(AE10<=5,"4-5 yrs",IF(AE10<=10,"6-10 yrs","10+ yrs")))) -> 0-1 yr | AK10: =IF(AG10>=3,"Overdue","Recent") -> Recent | AL10: =IF(W10="Yes",1,0)+IF(AD10<=2,1,0)+IF(Q10<=2,1,0)+IF(AG10>=3,1,0) -> 2 | AM10: =IF(AL10>=3,"High Risk",IF(AL10=2,"Medium Risk",IF(AL10=1,"Low Risk","Minimal Risk"))) -> Medium Risk | AN10: =IFERROR((S10-AVERAGEIF(P$2:P$1479,P10,S$2:S$1479))/AVERAGEIF(P$2:P$1479,P10,S$2:S$1479),0) -> -0.085061221 | AO10: =S10*12 -> 541572
A11: VK1500 | B11: 19 | C11: 18-25 | D11: No | E11: Travel_Rarely | F11: 1181 | G11: Administration | H11: 3 | I11: 1 | J11: Medical | K11: 201 | L11: 2 | M11: Female | N11: 3 | O11: 1 | P11: Laboratory Technician | Q11: 2 | R11: Single | S11: 61263 | T11: 6-10 LPA | U11: 382.89 | V11: 1 | W11: No | X11: 14 | Y11: 3 | Z11: 4 | AA11: 0 | AB11: 1 | AC11: 3 | AD11: 3 | AE11: 1 | AF11: 0 | AG11: 0 | AH11: 0 | AI11: =IF(D11="Yes",1,0) -> 0 | AJ11: =IF(AE11<=1,"0-1 yr",IF(AE11<=3,"2-3 yrs",IF(AE11<=5,"4-5 yrs",IF(AE11<=10,"6-10 yrs","10+ yrs")))) -> 0-1 yr | AK11: =IF(AG11>=3,"Overdue","Recent") -> Recent | AL11: =IF(W11="Yes",1,0)+IF(AD11<=2,1,0)+IF(Q11<=2,1,0)+IF(AG11>=3,1,0) -> 1 | AM11: =IF(AL11>=3,"High Risk",IF(AL11=2,"Medium Risk",IF(AL11=1,"Low Risk","Minimal Risk"))) -> Low Risk | AN11: =IFERROR((S11-AVERAGEIF(P$2:P$1479,P11,S$2:S$1479))/AVERAGEIF(P$2:P$1479,P11,S$2:S$1479),0) -> 0.18449906 | AO11: =S11*12 -> 735156
A12: VK1720 | B12: 19 | C12: 18-25 | D12: Yes | E12: Travel_Frequently | F12: 602 | G12: Sales | H12: 1 | I12: 1 | J12: Technical Degree | K12: 235 | L12: 3 | M12: Female | N12: 1 | O12: 1 | P12: Sales Representative | Q12: 1 | R12: Single | S12: 17023 | T12: 0-3 LPA | U12: 106.39 | V12: 0 | W12: No | X12: 21 | Y12: 4 | Z12: 1 | AA12: 0 | AB12: 1 | AC12: 5 | AD12: 4 | AE12: 0 | AF12: 0 | AG12: 0 | AH12: 0 | AI12: =IF(D12="Yes",1,0) -> 1 | AJ12: =IF(AE12<=1,"0-1 yr",IF(AE12<=3,"2-3 yrs",IF(AE12<=5,"4-5 yrs",IF(AE12<=10,"6-10 yrs","10+ yrs")))) -> 0-1 yr | AK12: =IF(AG12>=3,"Overdue","Recent") -> Recent | AL12: =IF(W12="Yes",1,0)+IF(AD12<=2,1,0)+IF(Q12<=2,1,0)+IF(AG12>=3,1,0) -> 1 | AM12: =IF(AL12>=3,"High Risk",IF(AL12=2,"Medium Risk",IF(AL12=1,"Low Risk","Minimal Risk"))) -> Low Risk | AN12: =IFERROR((S12-AVERAGEIF(P$2:P$1479,P12,S$2:S$1479))/AVERAGEIF(P$2:P$1479,P12,S$2:S$1479),0) -> -0.65489347 | AO12: =S12*12 -> 204276
A13: VK1780 | B13: 19 | C13: 18-25 | D13: Yes | E13: Travel_Rarely | F13: 303 | G13: Administration | H13: 2 | I13: 3 | J13: Life Sciences | K13: 243 | L13: 2 | M13: Male | N13: 2 | O13: 1 | P13: Laboratory Technician | Q13: 4 | R13: Single | S13: 42090 | T13: 3-6 LPA | U13: 263.06 | V13: 1 | W13: No | X13: 22 | Y13: 4 | Z13: 3 | AA13: 0 | AB13: 1 | AC13: 3 | AD13: 2 | AE13: 1 | AF13: 0 | AG13: 1 | AH13: 0 | AI13: =IF(D13="Yes",1,0) -> 1 | AJ13: =IF(AE13<=1,"0-1 yr",IF(AE13<=3,"2-3 yrs",IF(AE13<=5,"4-5 yrs",IF(AE13<=10,"6-10 yrs","10+ yrs")))) -> 0-1 yr | AK13: =IF(AG13>=3,"Overdue","Recent") -> Recent | AL13: =IF(W13="Yes",1,0)+IF(AD13<=2,1,0)+IF(Q13<=2,1,0)+IF(AG13>=3,1,0) -> 1 | AM13: =IF(AL13>=3,"High Risk",IF(AL13=2,"Medium Risk",IF(AL13=1,"Low Risk","Minimal Risk"))) -> Low Risk | AN13: =IFERROR((S13-AVERAGEIF(P$2:P$1479,P13,S$2:S$1479))/AVERAGEIF(P$2:P$1479,P13,S$2:S$1479),0) -> -0.18620431 | AO13: =S13*12 -> 505080
... A1479: VK12100 | B1479: 60 | C1479: 55+ | D1479: No | E1479: Travel_Rarely | F1479: 370 | G1479: Operations | H1479: 1 | I1479: 4 | J1479: Medical | K1479: 1697 | L1479: 3 | M1479: Male | N1479: 1 | O1479: 3 | P1479: Healthcare Representative | Q1479: 4 | R1479: Single | S1479: 87123 | T1479: 10+ LPA | U1479: 544.52 | V1479: 3 | W1479: No | X1479: 20 | Y1479: 4 | Z1479: 3 | AA1479: 1 | AB1479: 19 | AC1479: 2 | AD1479: 4 | AE1479: 1 | AF1479: 0 | AG1479: 0 | AH1479: 0 | AI1479: =IF(D1479="Yes",1,0) -> 0 | AJ1479: =IF(AE1479<=1,"0-1 yr",IF(AE1479<=3,"2-3 yrs",IF(AE1479<=5,"4-5 yrs",IF(AE1479<=10,"6-10 yrs","10+ yrs")))) -> 0-1 yr | AK1479: =IF(AG1479>=3,"Overdue","Recent") -> Recent | AL1479: =IF(W1479="Yes",1,0)+IF(AD1479<=2,1,0)+IF(Q1479<=2,1,0)+IF(AG1479>=3,1,0) -> 0 | AM1479: =IF(AL1479>=3,"High Risk",IF(AL1479=2,"Medium Risk",IF(AL1479=1,"Low Risk","Minimal Risk"))) -> Minimal Risk | AN1479: =IFERROR((S1479-AVERAGEIF(P$2:P$1479,P1479,S$2:S$1479))/AVERAGEIF(P$2:P$1479,P1479,S$2:S$1479),0) -> 0.80793836 | AO1479: =S1479*12 -> 1045476

Sheet Summary
A1: KPI Summary | E1: Attrition by Department | J1: Attrition by OverTime | O1: Attrition by Age Group
A2: Total Employees | B2: =COUNTA(Data!$G$2:$G$1479) -> 1478 | E2: Category | F2: Total | G2: Left | H2: Attrition Rate | J2: Category | K2: Total | L2: Left | M2: Attrition Rate | O2: Category | P2: Total | Q2: Left | R2: Attrition Rate
A3: Employees Left | B3: =COUNTIF(Data!$D$2:$D$1479,"Yes") -> 239 | E3: Administration | F3: =COUNTIF(Data!$G$2:$G$1479,E3) -> 425 | G3: =COUNTIFS(Data!$G$2:$G$1479,E3,Data!$D$2:$D$1479,"Yes") -> 88 | H3: =IFERROR(G3/F3,0) -> 0.20705882 | J3: No | K3: =COUNTIF(Data!$W$2:$W$1479,J3) -> 1059 | L3: =COUNTIFS(Data!$W$2:$W$1479,J3,Data!$D$2:$D$1479,"Yes") -> 109 | M3: =IFERROR(L3/K3,0) -> 0.10292729 | O3: 18-25 | P3: =COUNTIF(Data!$C$2:$C$1479,O3) -> 123 | Q3: =COUNTIFS(Data!$C$2:$C$1479,O3,Data!$D$2:$D$1479,"Yes") -> 45 | R3: =IFERROR(Q3/P3,0) -> 0.36585366
A4: Attrition Rate | B4: =COUNTIF(Data!$D$2:$D$1479,"Yes")/COUNTA(Data!$G$2:$G$1479) -> 0.16170501 | E4: Finance | F4: =COUNTIF(Data!$G$2:$G$1479,E4) -> 24 | G4: =COUNTIFS(Data!$G$2:$G$1479,E4,Data!$D$2:$D$1479,"Yes") -> 3 | H4: =IFERROR(G4/F4,0) -> 0.125 | J4: Yes | K4: =COUNTIF(Data!$W$2:$W$1479,J4) -> 419 | L4: =COUNTIFS(Data!$W$2:$W$1479,J4,Data!$D$2:$D$1479,"Yes") -> 130 | M4: =IFERROR(L4/K4,0) -> 0.31026253 | O4: 26-35 | P4: =COUNTIF(Data!$C$2:$C$1479,O4) -> 609 | Q4: =COUNTIFS(Data!$C$2:$C$1479,O4,Data!$D$2:$D$1479,"Yes") -> 116 | R4: =IFERROR(Q4/P4,0) -> 0.19047619
A5: Avg Monthly Income | B5: =AVERAGE(Data!$S$2:$S$1479) -> 49514.32 | E5: Human Resources | F5: =COUNTIF(Data!$G$2:$G$1479,E5) -> 39 | G5: =COUNTIFS(Data!$G$2:$G$1479,E5,Data!$D$2:$D$1479,"Yes") -> 9 | H5: =IFERROR(G5/F5,0) -> 0.23076923 | O5: 36-45 | P5: =COUNTIF(Data!$C$2:$C$1479,O5) -> 471 | Q5: =COUNTIFS(Data!$C$2:$C$1479,O5,Data!$D$2:$D$1479,"Yes") -> 43 | R5: =IFERROR(Q5/P5,0) -> 0.091295117
A6: Avg Tenure (yrs) | B6: =AVERAGE(Data!$AE$2:$AE$1479) -> 7.0142084 | E6: IT | F6: =COUNTIF(Data!$G$2:$G$1479,E6) -> 169 | G6: =COUNTIFS(Data!$G$2:$G$1479,E6,Data!$D$2:$D$1479,"Yes") -> 30 | H6: =IFERROR(G6/F6,0) -> 0.17751479 | O6: 46-55 | P6: =COUNTIF(Data!$C$2:$C$1479,O6) -> 228 | Q6: =COUNTIFS(Data!$C$2:$C$1479,O6,Data!$D$2:$D$1479,"Yes") -> 27 | R6: =IFERROR(Q6/P6,0) -> 0.11842105
A7: Avg Tenure - Left | B7: =AVERAGEIF(Data!$D$2:$D$1479,"Yes",Data!$AE$2:$AE$1479) -> 5.125523 | E7: Marketing | F7: =COUNTIF(Data!$G$2:$G$1479,E7) -> 67 | G7: =COUNTIFS(Data!$G$2:$G$1479,E7,Data!$D$2:$D$1479,"Yes") -> 10 | H7: =IFERROR(G7/F7,0) -> 0.14925373 | O7: 55+ | P7: =COUNTIF(Data!$C$2:$C$1479,O7) -> 47 | Q7: =COUNTIFS(Data!$C$2:$C$1479,O7,Data!$D$2:$D$1479,"Yes") -> 8 | R7: =IFERROR(Q7/P7,0) -> 0.17021277
A8: Avg Tenure - Active | B8: =AVERAGEIF(Data!$D$2:$D$1479,"No",Data!$AE$2:$AE$1479) -> 7.3785311 | E8: Operations | F8: =COUNTIF(Data!$G$2:$G$1479,E8) -> 540 | G8: =COUNTIFS(Data!$G$2:$G$1479,E8,Data!$D$2:$D$1479,"Yes") -> 45 | H8: =IFERROR(G8/F8,0) -> 0.083333333
E9: Sales | F9: =COUNTIF(Data!$G$2:$G$1479,E9) -> 214 | G9: =COUNTIFS(Data!$G$2:$G$1479,E9,Data!$D$2:$D$1479,"Yes") -> 54 | H9: =IFERROR(G9/F9,0) -> 0.25233645
E12: Attrition by Job Role | J12: Attrition by Work-Life Balance (1-4) | O12: Attrition by Marital Status
E13: Category | F13: Total | G13: Left | H13: Attrition Rate | J13: Category | K13: Total | L13: Left | M13: Attrition Rate | O13: Category | P13: Total | Q13: Left | R13: Attrition Rate
E14: Healthcare Representative | F14: =COUNTIF(Data!$P$2:$P$1479,E14) -> 133 | G14: =COUNTIFS(Data!$P$2:$P$1479,E14,Data!$D$2:$D$1479,"Yes") -> 9 | H14: =IFERROR(G14/F14,0) -> 0.067669173 | J14: 1 | K14: =COUNTIF(Data!$AD$2:$AD$1479,J14) -> 81 | L14: =COUNTIFS(Data!$AD$2:$AD$1479,J14,Data!$D$2:$D$1479,"Yes") -> 25 | M14: =IFERROR(L14/K14,0) -> 0.30864198 | O14: Married | P14: =COUNTIF(Data!$R$2:$R$1479,O14) -> 787 | Q14: =COUNTIFS(Data!$R$2:$R$1479,O14,Data!$D$2:$D$1479,"Yes") -> 90 | R14: =IFERROR(Q14/P14,0) -> 0.11435832
E15: Human Resources | F15: =COUNTIF(Data!$P$2:$P$1479,E15) -> 52 | G15: =COUNTIFS(Data!$P$2:$P$1479,E15,Data!$D$2:$D$1479,"Yes") -> 12 | H15: =IFERROR(G15/F15,0) -> 0.23076923 | J15: 2 | K15: =COUNTIF(Data!$AD$2:$AD$1479,J15) -> 348 | L15: =COUNTIFS(Data!$AD$2:$AD$1479,J15,Data!$D$2:$D$1479,"Yes") -> 59 | M15: =IFERROR(L15/K15,0) -> 0.16954023 | O15: Single | P15: =COUNTIF(Data!$R$2:$R$1479,O15) -> 691 | Q15: =COUNTIFS(Data!$R$2:$R$1479,O15,Data!$D$2:$D$1479,"Yes") -> 149 | R15: =IFERROR(Q15/P15,0) -> 0.21562952
E16: Laboratory Technician | F16: =COUNTIF(Data!$P$2:$P$1479,E16) -> 259 | G16: =COUNTIFS(Data!$P$2:$P$1479,E16,Data!$D$2:$D$1479,"Yes") -> 61 | H16: =IFERROR(G16/F16,0) -> 0.23552124 | J16: 3 | K16: =COUNTIF(Data!$AD$2:$AD$1479,J16) -> 895 | L16: =COUNTIFS(Data!$AD$2:$AD$1479,J16,Data!$D$2:$D$1479,"Yes") -> 128 | M16: =IFERROR(L16/K16,0) -> 0.14301676
E17: Manager | F17: =COUNTIF(Data!$P$2:$P$1479,E17) -> 102 | G17: =COUNTIFS(Data!$P$2:$P$1479,E17,Data!$D$2:$D$1479,"Yes") -> 5 | H17: =IFERROR(G17/F17,0) -> 0.049019608 | J17: 4 | K17: =COUNTIF(Data!$AD$2:$AD$1479,J17) -> 154 | L17: =COUNTIFS(Data!$AD$2:$AD$1479,J17,Data!$D$2:$D$1479,"Yes") -> 27 | M17: =IFERROR(L17/K17,0) -> 0.17532468
E18: Manufacturing Director | F18: =COUNTIF(Data!$P$2:$P$1479,E18) -> 146 | G18: =COUNTIFS(Data!$P$2:$P$1479,E18,Data!$D$2:$D$1479,"Yes") -> 10 | H18: =IFERROR(G18/F18,0) -> 0.068493151
E19: Research Director | F19: =COUNTIF(Data!$P$2:$P$1479,E19) -> 80 | G19: =COUNTIFS(Data!$P$2:$P$1479,E19,Data!$D$2:$D$1479,"Yes") -> 2 | H19: =IFERROR(G19/F19,0) -> 0.025
E20: Research Scientist | F20: =COUNTIF(Data!$P$2:$P$1479,E20) -> 293 | G20: =COUNTIFS(Data!$P$2:$P$1479,E20,Data!$D$2:$D$1479,"Yes") -> 48 | H20: =IFERROR(G20/F20,0) -> 0.16382253
E21: Sales Executive | F21: =COUNTIF(Data!$P$2:$P$1479,E21) -> 329 | G21: =COUNTIFS(Data!$P$2:$P$1479,E21,Data!$D$2:$D$1479,"Yes") -> 58 | H21: =IFERROR(G21/F21,0) -> 0.17629179
E22: Sales Representative | F22: =COUNTIF(Data!$P$2:$P$1479,E22) -> 84 | G22: =COUNTIFS(Data!$P$2:$P$1479,E22,Data!$D$2:$D$1479,"Yes") -> 34 | H22: =IFERROR(G22/F22,0) -> 0.4047619
E24: Attrition by Salary Slab
E25: Category | F25: Total | G25: Left | H25: Attrition Rate
E26: 0-3 LPA | F26: =COUNTIF(Data!$T$2:$T$1479,E26) -> 389 | G26: =COUNTIFS(Data!$T$2:$T$1479,E26,Data!$D$2:$D$1479,"Yes") -> 65 | H26: =IFERROR(G26/F26,0) -> 0.16709512
E27: 3-6 LPA | F27: =COUNTIF(Data!$T$2:$T$1479,E27) -> 355 | G27: =COUNTIFS(Data!$T$2:$T$1479,E27,Data!$D$2:$D$1479,"Yes") -> 51 | H27: =IFERROR(G27/F27,0) -> 0.14366197
E28: 6-10 LPA | F28: =COUNTIF(Data!$T$2:$T$1479,E28) -> 484 | G28: =COUNTIFS(Data!$T$2:$T$1479,E28,Data!$D$2:$D$1479,"Yes") -> 75 | H28: =IFERROR(G28/F28,0) -> 0.15495868
E29: 10+ LPA | F29: =COUNTIF(Data!$T$2:$T$1479,E29) -> 250 | G29: =COUNTIFS(Data!$T$2:$T$1479,E29,Data!$D$2:$D$1479,"Yes") -> 48 | H29: =IFERROR(G29/F29,0) -> 0.192
